wsclean/main.py
wsclean-1.0.0.dist-info/entry_points.txt
wsclean-1.0.0.dist-info/LICENSE
wsclean-1.0.0.dist-info/WHEEL
wsclean-1.0.0.dist-info/METADATA
wsclean-1.0.0.dist-info/RECORD
