Metadata-Version: 2.1
Name: wsclean
Version: 1.0.0
Summary: Cleans the contents of your clipboard by removing redundant whitespace and new lines.
License: BSD-3-Clause
Author: Elias Gabriel
Author-email: me@eliasfgabriel.com
Requires-Python: >=3.6,<4.0
Classifier: License :: OSI Approved :: BSD License
Classifier: Programming Language :: Python :: 3
Classifier: Programming Language :: Python :: 3.10
Classifier: Programming Language :: Python :: 3.6
Classifier: Programming Language :: Python :: 3.7
Classifier: Programming Language :: Python :: 3.8
Classifier: Programming Language :: Python :: 3.9
Requires-Dist: pyperclip (>=1.8.2,<2.0.0)
Requires-Dist: typer (>=0.4.0,<0.5.0)
